connectHFU/__init__.py
connectHFU/client.py
connectHFU/server.py
connectpy/__init__.py
connectpy/client.py
connectpy/server.py
connectHFU-0.3.dist-info/LICENSE
connectHFU-0.3.dist-info/METADATA
connectHFU-0.3.dist-info/WHEEL
connectHFU-0.3.dist-info/top_level.txt
connectHFU-0.3.dist-info/RECORD
