Metadata-Version: 2.1
Name: connectHFU
Version: 0.3
Summary: Allows connections between a Server and Client(s)
Author: ExplosiveHedgehog
License: MIT
License-File: LICENSE
